.DS_Store
hybra/.DS_Store
hybra/__init__.py
hybra/core.py
hybra/descriptives.py
hybra/wordclouds.py
hybra/analysis/.DS_Store
hybra/analysis/__init__.py
hybra/analysis/run.py
hybra/analysis/runr.py
hybra/analysis/save_r.r
hybra/analysis/topicmodel/__init__.py
hybra/analysis/topicmodel/check_best_fit.r
hybra/analysis/topicmodel/check_k.r
hybra/analysis/topicmodel/create_dtm.r
hybra/analysis/topicmodel/create_topics.r
hybra/analysis/topicmodel/lemmatize.py
hybra/analysis/topicmodel/print_assigments.r
hybra/analysis/topicmodel/print_words.r
hybra/analysis/topicmodel/stm.r
hybra/analysis/topicmodel/stop_generic.txt
hybra/analysis/topicmodel/topics.r
hybra/helpers/__init__.py
hybra/helpers/counters.py
hybra/helpers/exporter.py
hybra/helpers/filters.py
hybra/helpers/urls.py
hybra/loaders/__init__.py
hybra/loaders/common.py
hybra/loaders/facebook.py
hybra/loaders/futusome.py
hybra/loaders/mediacloud.py
hybra/loaders/news.py
hybra/loaders/s24.py
hybra/loaders/twitter.py
hybra/network/__init__.py
hybra/network/module_network.py
hybra/network/network.css
hybra/network/network.html
hybra/network/network_canvas.js
hybra/network/network_svg.js
hybra/timeline/__init__.py
hybra/timeline/module_timeline.py
hybra/timeline/timeline.css
hybra/timeline/timeline.html
hybra/timeline/timeline.js
hybra_core-0.1.2a1.dist-info/DESCRIPTION.rst
hybra_core-0.1.2a1.dist-info/METADATA
hybra_core-0.1.2a1.dist-info/RECORD
hybra_core-0.1.2a1.dist-info/WHEEL
hybra_core-0.1.2a1.dist-info/metadata.json
hybra_core-0.1.2a1.dist-info/top_level.txt
