Metadata-Version: 2.0
Name: hybra-core
Version: 0.1.2a1
Summary: Toolkit for data management and analysis.
Home-page: https://github.com/HIIT/hybra-core
Author: Matti Nelimarkka, Juho Pääkkönen, Arto Kekkonen
Author-email: matti.nelimarkka@aalto.fi, juho.paakkonen@aalto.fi, arto.kekkonen@helsinki.fi
License: MIT
Keywords: data management,data analysis
Platform: UNKNOWN
Classifier: Development Status :: 3 - Alpha
Classifier: Intended Audience :: Science/Research
Classifier: Topic :: Scientific/Engineering
Classifier: License :: OSI Approved :: MIT License
Classifier: Programming Language :: Python :: 2.7
Classifier: Programming Language :: JavaScript
Requires-Dist: dateparser (>=0.5.1)
Requires-Dist: GitPython (>=2.0.6)
Requires-Dist: jupyter (>=1.0.0)
Requires-Dist: jupyter-client (>=4.3.0)
Requires-Dist: jupyter-console (>=4.1.1)
Requires-Dist: jupyter-core (>=4.1.0)
Requires-Dist: matplotlib (>=1.5.3)
Requires-Dist: nbstripout (>=0.2.9)
Requires-Dist: networkx (>=1.11)
Requires-Dist: numpy (>=1.11.0)
Requires-Dist: requests (>=2.9.1)
Requires-Dist: scikit-learn (>=0.17.1)
Requires-Dist: scipy (>=0.17.1)
Requires-Dist: XlsxWriter (>=0.9.6)
Requires-Dist: wordcloud (>=1.2.1)
Requires-Dist: tldextract (>=2.1.0)
Requires-Dist: pandas (>=0.22.0)
Requires-Dist: rpy2 (<=2.8.6)
